setup.py
taigi_tools/__init__.py
taigi_tools/hanji.py
taigi_tools/tailo.py
taigi_tools/tailotest.py
taigi_tools.egg-info/PKG-INFO
taigi_tools.egg-info/SOURCES.txt
taigi_tools.egg-info/dependency_links.txt
taigi_tools.egg-info/not-zip-safe
taigi_tools.egg-info/top_level.txt