Metadata-Version: 1.0
Name: taigi-tools
Version: 0.2
Summary: Tools for Taiwanese pinyin and character conversions
Home-page: UNKNOWN
Author: Edward Greve
Author-email: edward.greve@gmail.com
License: MIT
Keywords: taiwanese,pinyin
Platform: UNKNOWN
